valorantproapi/__init__.py
valorantproapi/data.py
valorantproapi-1.1.3.dist-info/METADATA
valorantproapi-1.1.3.dist-info/WHEEL
valorantproapi-1.1.3.dist-info/licenses/LICENSE
valorantproapi-1.1.3.dist-info/RECORD
