Metadata-Version: 2.4
Name: valorantproapi
Version: 1.1.3
Summary: A python library to retrieve data from pro matches of valorant registered on the site https://vlr.gg/.
Project-URL: Homepage, https://github.com/ThorkildFregi/valorantproapi
Project-URL: Issues, https://github.com/ThorkildFregi/valorantproapi/issues
Author-email: Gabriel Bermes--Poupeau <gabrielbermesp@gmail.com>
License-Expression: Apache-2.0
License-File: LICENSE
Classifier: Operating System :: OS Independent
Classifier: Programming Language :: Python :: 3
Requires-Python: >=3.9
